pipelinedb/__init__.py
pipelinedb/client.py
pipelinedb/errors.py
pipelinedb_py-1.0.1.dev1.dist-info/DESCRIPTION.rst
pipelinedb_py-1.0.1.dev1.dist-info/METADATA
pipelinedb_py-1.0.1.dev1.dist-info/RECORD
pipelinedb_py-1.0.1.dev1.dist-info/WHEEL
pipelinedb_py-1.0.1.dev1.dist-info/metadata.json
pipelinedb_py-1.0.1.dev1.dist-info/top_level.txt
