Metadata-Version: 2.0
Name: pipelinedb-py
Version: 1.0.1.dev1
Summary: A pipelinedb client python project
Home-page: https://github.com/calvinjiang/pipelinedb-py
Author: Shihui He,Hua Jiang
Author-email: jianghuachinacom@163.com
License: MIT
Keywords: pipelinedb client python
Platform: UNKNOWN
Classifier: Development Status :: 4 - Beta
Classifier: Intended Audience :: Developers
Classifier: Topic :: Software Development :: Build Tools
Classifier: License :: OSI Approved :: MIT License
Classifier: Programming Language :: Python :: 2.6
Classifier: Programming Language :: Python :: 2.7
Classifier: Programming Language :: Python :: 3
Classifier: Programming Language :: Python :: 3.3
Classifier: Programming Language :: Python :: 3.4
Classifier: Programming Language :: Python :: 3.5
Requires-Dist: common-utils
Requires-Dist: psycopg2
